autostarter/__init__.py
autostarter/autostarter.py
autostarter/util.py
autostarter/systems/__init__.py
autostarter/systems/darwin.py
autostarter/systems/linux.py
autostarter/systems/windows.py
autostarter-0.0.2.dist-info/LICENSE
autostarter-0.0.2.dist-info/METADATA
autostarter-0.0.2.dist-info/WHEEL
autostarter-0.0.2.dist-info/top_level.txt
autostarter-0.0.2.dist-info/RECORD
