Metadata-Version: 2.1
Name: autostarter
Version: 0.0.2
Summary: A module for adding and removing startup scripts on Windows, Mac, and Linux systems
Home-page: https://github.com/ctrlsam/autostarter
Author: Sam Redmond
Author-email: samredmondtech@gmail.com
Classifier: Programming Language :: Python :: 3
Classifier: License :: OSI Approved :: MIT License
Classifier: Operating System :: OS Independent
License-File: LICENSE
